puresnmp_plugins/priv/aes.py
puresnmp_plugins/priv/des.py
puresnmp_crypto-1.0.1.post1.dist-info/METADATA
puresnmp_crypto-1.0.1.post1.dist-info/WHEEL
puresnmp_crypto-1.0.1.post1.dist-info/top_level.txt
puresnmp_crypto-1.0.1.post1.dist-info/RECORD
